{"authors": [], "date_download": "2022-10-25 23:38:23", "date_modify": "2022-10-25 23:38:23", "date_publish": null, "description": "The online home of ‘Sunday Routine,’ featuring a complete archive of columns that chronicle the Sundays of newsworthy New Yorkers, going back to 2009.", "filename": "column_sunday-routine_1666741103.html", "image_url": "https://static01.nyt.com/newsgraphics/images/icons/defaultPromoCrop.png", "language": "en", "localpath": "/Users/matthewwhite/news-please-repo//data/2022/10/25/nytimes.com/column_sunday-routine_1666741103.html", "title": "Sunday Routine", "title_page": "Sunday Routine - The New York Times", "title_rss": "NULL", "source_domain": "nytimes.com", "maintext": "How Dr. Becky Spends Her Sundays\nThe parenting expert tries to fit it all in, from workouts and pancakes to game time and play dates.", "url": "https://www.nytimes.com/column/sunday-routine"}