{"authors": [], "date_download": "2022-10-25 22:57:21", "date_modify": "2022-10-25 22:57:21", "date_publish": null, "description": "Feast on recipes, food writing and culinary inspiration from Sam Sifton and NYT Cooking.", "filename": "newsletters_cooking_1666738641.html", "image_url": "https://static01.nyt.com/email-images/Newsletter%20Icons/Cooking.png", "language": "en", "localpath": "/Users/matthewwhite/news-please-repo//data/2022/10/25/nytimes.com/newsletters_cooking_1666738641.html", "title": "Cooking Newsletter", "title_page": "Cooking Newsletter - The New York Times", "title_rss": "NULL", "source_domain": "nytimes.com", "maintext": "Cooking\nFeast on recipes, food writing and culinary inspiration from Sam Sifton and NYT Cooking.", "url": "https://www.nytimes.com/newsletters/cooking"}