{"authors": [], "date_download": "2022-10-25 23:52:00", "date_modify": "2022-10-25 23:52:00", "date_publish": null, "description": "Articles in this series examine the reshaping of regulations under the Trump administration.", "filename": "series_trump-rules-regulations_1666741920.html", "image_url": "https://static01.nyt.com/newsgraphics/images/icons/defaultPromoCrop.png", "language": "en", "localpath": "/Users/matthewwhite/news-please-repo//data/2022/10/25/nytimes.com/series_trump-rules-regulations_1666741920.html", "title": "Trump Rules", "title_page": "Trump Rules - The New York Times", "title_rss": "NULL", "source_domain": "nytimes.com", "maintext": "Trump Rules\nWhy Has the E.P.A. Shifted on Toxic Chemicals? An Industry Insider Helps Call the Shots\nA scientist who worked for the chemical industry now shapes policy on hazardous chemicals. Within the E.P.A., there is fear that public health is at risk. (At right, a signing ceremony for new rules on toxic chemicals.)", "url": "https://www.nytimes.com/series/trump-rules-regulations"}